{
	"displayName": "Git",
	"description": " Integração Git SCM",
	"command.continueInLocalClone": "Clone o repositório localmente e abra na área de trabalho",
	"command.continueInLocalClone.qualifiedName": "Continue trabalhando no novo clone local",
	"command.clone": "Clonar",
	"command.cloneRecursive": "Clonar (Recursivo)",
	"command.init": "Inicializar Repostório",
	"command.openRepository": "Abrir Repositório",
	"command.reopenClosedRepositories": "Reabrir Repositórios Fechados...",
	"command.close": "Fechar Repositório",
	"command.closeOtherRepositories": "Fechar Outros Repositórios",
	"command.openWorktree": "Abrir WorkTree nessa janela",
	"command.openWorktreeInNewWindow": "Abrir WorkTree em outra janela",
	"command.refresh": "Recarregar",
	"command.compareWithWorkspace": "Comparar com Workplace",
	"command.openChange": "Abrir Mudanças",
	"command.openAllChanges": "Open All Changes",
	"command.openFile": "Abrir Arquivo",
	"command.openHEADFile": "Abrir arquivo (Head)",
	"command.stage": "Preparar Alterações",
	"command.stageAll": "Preparar Todas as Alterações",
	"command.stageAllTracked": "Preparar Todas as Alterações Rastreáveis",
	"command.stageAllUntracked": "Preparar Todas as Alterações Não Rastreáveis",
	"command.stageAllMerge": "Preparar Todas as Alterações de Mesclagem",
	"command.stageSelectedRanges": "Preparar Intervalos Selecionados",
	"command.revertSelectedRanges": "Reverter Intervalos Selecionados",
	"command.stageChange": "Preparar Alterações",
	"command.stageSelection": "Preparar Seleção",
	"command.stageBlock": "Blockar Preparação",
	"command.revertChange": "Reverter Alteração",
	"command.unstage": "Despreparar Alterações",
	"command.unstageAll": "Despreparar Todas as Alterações",
	"command.unstageChange": "Despreparar Alteração",
	"command.unstageSelectedRanges": "Remover Intervalos Selecionados da Preparação",
	"command.rename": "Renomear",
	"command.clean": "Descartar alterações",
	"command.cleanAll": "Descartar Todas as Alterações",
	"command.cleanAllTracked": "Descartar Todas as Alterações Rastreaveis",
	"command.cleanAllUntracked": "Descartar Todas as Alterações Não Rastreaveis",
	"command.closeAllDiffEditors": "Fechar Todos os Editores de Diferença",
	"command.closeAllUnmodifiedEditors": "Fechar Todos os Editores Não Modificados",
	"command.commit": "Commit",
	"command.commitAmend": "Commit (Alterar)",
	"command.commitSigned": "Commit (Assinado)",
	"command.commitStaged": "Commit Preparado",
	"command.commitEmpty": "Commit Vazio",
	"command.commitStagedSigned": "Commit Preparado (Assinado)",
	"command.commitStagedAmend": "Commit Preparado (Alterar)",
	"command.commitAll": "Commit Tudo",
	"command.commitAllSigned": "Commit Tudo (Assinado)",
	"command.commitAllAmend": "Commit Tudo (Alterar)",
	"command.commitNoVerify": "Commit (Sem Verificação)",
	"command.commitStagedNoVerify": "Commit Preparado (Sem Verificação)",
	"command.commitEmptyNoVerify": "Commit Vazio (Sem Verificação)",
	"command.commitStagedSignedNoVerify": "Commit Preparado (Assinado, Sem Verificação)",
	"command.commitAmendNoVerify": "Commit (Alterar, Sem Verificação)",
	"command.commitSignedNoVerify": "Commit (Assinado, Sem Verificação)",
	"command.commitStagedAmendNoVerify": "Commit Preparado (Alterar, Sem Verificação)",
	"command.commitAllNoVerify": "Commit Tudo (Sem Verificação)",
	"command.commitAllSignedNoVerify": "Commit Tudo (Assinado, Sem Verificação)",
	"command.commitAllAmendNoVerify": "Commit Tudo (Alterar, Sem Verificação)",
	"command.commitMessageAccept": "Aceitar Mensagem de Commit",
	"command.commitMessageDiscard": "Descartar Mensagem de Commit",
	"command.restoreCommitTemplate": "Restaurar Modelo de Commit",
	"command.undoCommit": "Desfazer Último Commit",
	"command.checkout": "Trocar Para...",
	"command.checkoutDetached": "Trocar Para (Destacado)...",
	"command.branch": "Criar Branch...",
	"command.branchFrom": "Criar Branch A Partir de...",
	"command.deleteBranch": "Excluir Branch...",
	"command.deleteRemoteBranch": "Excluir Branch Remota...",
	"command.renameBranch": "Renomear Branch...",
	"command.cherryPick": "Cherry Pick...",
	"command.cherryPickAbort": "Abortar Cherry Pick",
	"command.merge": "Mesclar...",
	"command.merge2": "Mesclar",
	"command.mergeAbort": "Abortar Mesclagem",
	"command.rebase": "Rebase Branch...",
	"command.rebase2": "Rebase",
	"command.createFrom": "Criar a partir de...",
	"command.createTag": "Criar Tag...",
	"command.deleteTag": "Excluir Tag...",
	"command.migrateWorktreeChanges": "Migrar Alterações do Worktree...",
	"command.createWorktree": "Criar Worktree...",
	"command.deleteWorktree": "Excluir Worktree...",
	"command.deleteWorktree2": "Excluir Worktree",
	"command.deleteRemoteTag": "Excluir Tag Remota...",
	"command.fetch": "Buscar",
	"command.fetchPrune": "Buscar (Podar)",
	"command.fetchAll": "Buscar de Todos os Remotos",
	"command.pull": "Pull",
	"command.pullRebase": "Pull (Rebase)",
	"command.pullFrom": "Pull de...",
	"command.push": "Push",
	"command.pushForce": "Push (Forçado)",
	"command.pushTo": "Push para...",
	"command.pushToForce": "Push para... (Forçado)",
	"command.pushFollowTags": "Push (Seguir Tags)",
	"command.pushFollowTagsForce": "Push (Seguir Tags, Forçado)",
	"command.pushTags": "Push de Tags",
	"command.addRemote": "Adicionar Remoto...",
	"command.removeRemote": "Remover Remoto",
	"command.sync": "Sincronizar",
	"command.syncRebase": "Sincronizar (Rebase)",
	"command.publish": "Publicar Branch...",
	"command.showOutput": "Exibir Saída do Git",
	"command.ignore": "Adicionar ao .gitignore",
	"command.revealInExplorer": "Revelar na Visualização do Explorer",
	"command.revealFileInOS.linux": "Abrir Pasta Contendo",
	"command.revealFileInOS.mac": "Revelar no Finder",
	"command.revealFileInOS.windows": "Revelar no Explorador de Arquivos",
	"command.rebaseAbort": "Abortar Rebase",
	"command.stashIncludeUntracked": "Stash (Incluir Não Rastreáveis)",
	"command.stash": "Stash",
	"command.stashStaged": "Stash Preparado",
	"command.stashPop": "Restaurar Stash...",
	"command.stashPopLatest": "Restaurar Último Stash",
	"command.stashPopEditor": "Restaurar Stash",
	"command.stashApply": "Aplicar Stash...",
	"command.stashApplyLatest": "Aplicar Último Stash",
	"command.stashApplyEditor": "Aplicar Stash",
	"command.stashDrop": "Descartar Stash...",
	"command.stashDropAll": "Descartar Todos os Stashes...",
	"command.stashDropEditor": "Descartar Stash",
	"command.stashView": "Visualizar Stash...",
	"command.stashView2": "Visualizar Stash",
	"command.timelineOpenDiff": "Abrir Alterações",
	"command.timelineCopyCommitId": "Copiar ID do Commit",
	"command.timelineCopyCommitMessage": "Copiar Mensagem do Commit",
	"command.timelineSelectForCompare": "Selecionar para Comparar",
	"command.timelineCompareWithSelected": "Comparar com Selecionado",
	"command.manageUnsafeRepositories": "Gerenciar Repositórios Não Confiáveis",
	"command.openRepositoriesInParentFolders": "Abrir Repositórios nas Pastas Pai",
	"command.viewChanges": "Abrir Alterações",
	"command.viewStagedChanges": "Abrir Alterações Preparadas",
	"command.viewUntrackedChanges": "Abrir Alterações Não Rastreáveis",
	"command.viewCommit": "Abrir Commit",
	"command.graphCheckout": "Trocar Para",
	"command.graphCheckoutDetached": "Trocar Para (Destacado)",
	"command.graphCherryPick": "Cherry Pick",
	"command.graphDeleteBranch": "Excluir Branch",
	"command.graphDeleteTag": "Excluir Tag",
	"command.graphCompareRef": "Comparar com...",
	"command.graphCompareWithMergeBase": "Comparar com Base da Mesclagem",
	"command.graphCompareWithRemote": "Comparar com Remoto",
	"command.deleteRef": "Excluir",
	"command.blameToggleEditorDecoration": "Alternar Decoração do Editor do Git Blame",
	"command.blameToggleStatusBarItem": "Alternar Item de Barra de Status do Git Blame",
	"command.api.getRepositories": "Obter Repositórios",
	"command.api.getRepositoryState": "Obter Estado do Repositório",
	"command.api.getRemoteSources": "Obter Fontes Remotas",
	"command.git.acceptMerge": "Concluir Mesclagem",
	"command.git.openMergeEditor": "Resolver no Editor de Mesclagem",
	"command.git.runGitMerge": "Computar Conflitos com Git",
	"command.git.runGitMergeDiff3": "Computar Conflitos com Git (Diff3)",
	"config.enabled": "Se o Git está habilitado.",
	"config.path": "Caminho e nome do executável git, ex: `C:\\Program Files\\Git\\bin\\git.exe` (Windows). Pode ser um array de strings com múltiplos caminhos.",
	"config.autoRepositoryDetection": "Configura quando os repositórios devem ser detectados automaticamente.",
	"config.autoRepositoryDetection.true": "Verificar subpastas da pasta aberta e pastas pai dos arquivos abertos.",
	"config.autoRepositoryDetection.false": "Desativar verificação automática de repositórios.",
	"config.autoRepositoryDetection.subFolders": "Verificar subpastas da pasta atualmente aberta.",
	"config.autoRepositoryDetection.openEditors": "Verificar pastas pai dos arquivos abertos.",
	"config.autorefresh": "Se a atualização automática está habilitada.",
	"config.autofetch": "Quando verdadeiro, commits serão buscados automaticamente do remoto padrão do repositório atual. `all` busca de todos os remotos.",
	"config.autofetchPeriod": "Duração em segundos entre cada git fetch automático, quando `#git.autofetch#` estiver habilitado.",
	"config.confirmSync": "Confirmar antes de sincronizar repositórios Git.",
	"config.countBadge": "Controla o contador de alterações do Git.",
	"config.countBadge.all": "Contar todas as alterações.",
	"config.countBadge.tracked": "Contar apenas alterações rastreadas.",
	"config.countBadge.off": "Desligar contador.",
	"config.checkoutType": "Controla que tipo de referências Git são listadas ao executar `Trocar Para...`.",
	"config.checkoutType.local": "Branches Locais",
	"config.checkoutType.tags": "Tags",
	"config.checkoutType.remote": "Branches Remotas",
	"config.defaultBranchName": "O nome do branch padrão (exemplo: main, trunk, development) ao inicializar um novo repositório Git. Quando vazio, será usado o nome do branch padrão configurado no Git. **Nota:** Requer Git versão `2.28.0` ou superior.",
	"config.branchPrefix": "Prefixo usado ao criar um novo branch.",
	"config.branchProtection": "Lista de branches protegidos. Por padrão, um aviso é mostrado antes de alterações serem commitadas em um branch protegido. O aviso pode ser controlado usando a configuração `#git.branchProtectionPrompt#`.",
	"config.branchProtectionPrompt": "Controla se um aviso é exibido antes de commit em um branch protegido.",
	"config.branchProtectionPrompt.alwaysCommit": "Sempre commit alterações no branch protegido.",
	"config.branchProtectionPrompt.alwaysCommitToNewBranch": "Sempre commit alterações em um novo branch.",
	"config.branchProtectionPrompt.alwaysPrompt": "Sempre exibir aviso antes de commit em um branch protegido.",
	"config.branchRandomNameDictionary": "Lista de dicionários usados para gerar nomes aleatórios de branch. Cada valor representa o dicionário para gerar um segmento do nome. Dicionários suportados: `adjectives`, `animals`, `colors` e `numbers`.",
	"config.branchRandomNameDictionary.adjectives": "Um adjetivo aleatório",
	"config.branchRandomNameDictionary.animals": "Nome de um animal aleatório",
	"config.branchRandomNameDictionary.colors": "Nome de uma cor aleatória",
	"config.branchRandomNameDictionary.numbers": "Número aleatório entre 100 e 999",
	"config.branchRandomNameEnable": "Controla se um nome aleatório é gerado ao criar um novo branch.",
	"config.branchValidationRegex": "Expressão regular para validar novos nomes de branch.",
	"config.branchWhitespaceChar": "Caractere para substituir espaços em nomes de branch novos e separar segmentos de nomes aleatórios.",
	"config.ignoreLegacyWarning": "Ignora aviso legado do Git.",
	"config.ignoreMissingGitWarning": "Ignora aviso quando o Git não está instalado.",
	"config.ignoreWindowsGit27Warning": "Ignora aviso quando Git 2.25 - 2.26 está instalado no Windows.",
	"config.ignoreLimitWarning": "Ignora aviso quando há muitas alterações em um repositório.",
	"config.ignoreRebaseWarning": "Ignora aviso quando parece que o branch foi rebaseado durante um pull.",
	"config.defaultCloneDirectory": "Local padrão para clonar um repositório Git.",
	"config.useEditorAsCommitInput": "Controla se um editor de texto completo será usado para escrever mensagens de commit quando nenhuma mensagem for fornecida na caixa de commit.",
	"config.verboseCommit": "Habilita saída detalhada quando `#git.useEditorAsCommitInput#` estiver habilitado.",
	"config.enableSmartCommit": "Comitar todas as alterações quando não houver alterações preparadas.",
	"config.smartCommitChanges": "Controla quais alterações são automaticamente preparadas pelo Smart Commit.",
	"config.smartCommitChanges.all": "Preparar todas as alterações automaticamente.",
	"config.smartCommitChanges.tracked": "Preparar apenas alterações rastreadas automaticamente.",
	"config.suggestSmartCommit": "Sugere habilitar smart commit (comitar todas as alterações quando não houver alterações preparadas).",
	"config.enableCommitSigning": "Habilita assinatura de commits com GPG, X.509 ou SSH.",
	"config.discardAllScope": "Controla quais alterações são descartadas pelo comando `Descartar todas as alterações`. `all` descarta todas as alterações. `tracked` descarta apenas arquivos rastreados. `prompt` mostra aviso toda vez que a ação for executada.",
	"config.decorations.enabled": "Controla se o Git contribui com cores e badges na visualização do Explorer e Editores Abertos.",
	"config.enableStatusBarSync": "Controla se o comando Git Sync aparece na barra de status.",
	"config.followTagsWhenSync": "Enviar todas as tags anotadas ao executar o comando de sincronização.",
	"config.replaceTagsWhenPull": "Substituir automaticamente tags locais pelas remotas em caso de conflito durante pull.",
	"config.promptToSaveFilesBeforeStash": "Controla se o Git verifica arquivos não salvos antes de stashing.",
	"config.promptToSaveFilesBeforeStash.always": "Verificar todos os arquivos não salvos.",
	"config.promptToSaveFilesBeforeStash.staged": "Verificar apenas arquivos staged não salvos.",
	"config.promptToSaveFilesBeforeStash.never": "Desativar verificação.",
	"config.promptToSaveFilesBeforeCommit": "Controla se o Git verifica arquivos não salvos antes de commit.",
	"config.promptToSaveFilesBeforeCommit.always": "Verificar todos os arquivos não salvos.",
	"config.promptToSaveFilesBeforeCommit.staged": "Verificar apenas arquivos staged não salvos.",
	"config.promptToSaveFilesBeforeCommit.never": "Desativar verificação.",
	"config.postCommitCommand": "Executar comando Git após commit bem-sucedido.",
	"config.postCommitCommand.none": "Não executar nenhum comando após commit.",
	"config.postCommitCommand.push": "Executar 'git push' após commit bem-sucedido.",
	"config.postCommitCommand.sync": "Executar 'git pull' e 'git push' após commit bem-sucedido.",
	"config.rememberPostCommitCommand": "Lembrar último comando Git executado após commit.",
	"config.openAfterClone": "Controla se um repositório será aberto automaticamente após clone.",
	"config.openAfterClone.always": "Sempre abrir na janela atual.",
	"config.openAfterClone.alwaysNewWindow": "Sempre abrir em uma nova janela.",
	"config.openAfterClone.whenNoFolderOpen": "Abrir na janela atual apenas se nenhuma pasta estiver aberta.",
	"config.openAfterClone.prompt": "Sempre perguntar antes de abrir.",
	"config.showInlineOpenFileAction": "Controla se a ação de Abrir Arquivo é mostrada inline na visualização de alterações do Git.",
	"config.showPushSuccessNotification": "Controla se uma notificação é exibida quando push for bem-sucedido.",
	"config.inputValidation": "Controla se diagnósticos de validação da mensagem de commit são exibidos.",
	"config.inputValidationLength": "Controla o limite de tamanho da mensagem de commit para exibir aviso.",
	"config.inputValidationSubjectLength": "Controla o limite de tamanho do assunto da mensagem de commit para exibir aviso. Deixe vazio para herdar `#git.inputValidationLength#`.",
	"config.detectSubmodules": "Controla se submódulos Git são detectados automaticamente.",
	"config.detectSubmodulesLimit": "Controla limite de submódulos Git detectados.",
	"config.detectWorktrees": "Controla se worktrees Git são detectados automaticamente.",
	"config.detectWorktreesLimit": "Controla limite de worktrees Git detectados.",
	"config.alwaysShowStagedChangesResourceGroup": "Sempre mostrar o grupo de recursos de Alterações Preparadas.",
	"config.alwaysSignOff": "Controla a flag de signoff para todos os commits.",
	"config.ignoreSubmodules": "Ignorar modificações em submódulos na árvore de arquivos.",
	"config.ignoredRepositories": "Lista de repositórios Git a ignorar.",
	"config.scanRepositories": "Lista de caminhos para procurar repositórios Git.",
	"config.commandsToLog": {
		"message": "Lista de comandos Git (ex: commit, push) cujo `stdout` será registrado na [saída do Git](command:git.showOutput). Se houver hook configurado no cliente, o `stdout` do hook também será registrado na [saída do Git](command:git.showOutput).",
		"comment": [
			"{Locked='](command:git.showOutput'}",
			"Não traduzir a parte 'command:*' dentro de '(..)'. É uma sintaxe interna do VS Code",
			"Certifique-se de que não haja espaço entre o colchete direito e o parêntese esquerdo:  ]( isso é uma sintaxe interna de links"
		]
	},
	"config.showProgress": "Controla se ações do Git devem mostrar progresso.",
"config.rebaseWhenSync": "Forçar Git a usar rebase ao executar o comando de sincronização.",
"config.confirmEmptyCommits": "Sempre confirmar a criação de commits vazios com o comando 'Git: Commit Empty'.",
"config.fetchOnPull": "Quando habilitado, busca todos os branches ao executar pull. Caso contrário, busca apenas o branch atual.",
"config.pullBeforeCheckout": "Controla se um branch sem commits a enviar é avançado (fast-forward) antes de ser feito checkout.",
"config.pullTags": "Buscar todas as tags ao executar pull.",
"config.pruneOnFetch": "Executar prune ao buscar (fetch).",
"config.autoStash": "Guardar alterações (stash) antes do pull e restaurá-las após pull bem-sucedido.",
"config.allowForcePush": "Controla se push forçado (force push, com ou sem lease) é permitido.",
"config.useForcePushWithLease": "Controla se o push forçado deve usar a variante mais segura 'force-with-lease'.",
"config.useForcePushIfIncludes": "Controla se o push forçado deve usar a variante mais segura 'force-if-includes'. **Nota:** Requer `#git.useForcePushWithLease#` habilitado e Git `2.30.0` ou superior.",
"config.confirmForcePush": "Controla se é solicitado confirmação antes de um push forçado.",
"config.allowNoVerifyCommit": "Controla se commits sem rodar hooks pre-commit e commit-msg são permitidos.",
"config.confirmNoVerifyCommit": "Controla se é solicitado confirmação antes de commit sem verificação.",
"config.closeDiffOnOperation": "Controla se o editor de diff deve ser fechado automaticamente ao realizar stash, commit, descartar, stage ou unstage.",
"config.openDiffOnClick": "Controla se o editor de diff deve ser aberto ao clicar em uma alteração. Caso contrário, abre o editor normal.",
"config.supportCancellation": "Controla se aparece notificação durante ação de sincronização, permitindo cancelar a operação.",
"config.branchSortOrder": "Controla a ordem de classificação dos branches.",
"config.untrackedChanges": "Controla o comportamento das alterações não rastreadas.",
"config.untrackedChanges.mixed": "Todas alterações, rastreadas e não rastreadas, aparecem juntas e se comportam igualmente.",
"config.untrackedChanges.separate": "Alterações não rastreadas aparecem separadas na visualização de Controle de Código Fonte e são excluídas de várias ações.",
"config.untrackedChanges.hidden": "Alterações não rastreadas são ocultas e excluídas de várias ações.",
"config.requireGitUserConfig": "Controla se é obrigatório ter configuração de usuário Git ou permitir que o Git estime se estiver faltando.",
"config.showCommitInput": "Controla se o campo de commit é mostrado no painel de Controle de Código Fonte do Git.",
"config.terminalAuthentication": "Controla se o VS Code será o manipulador de autenticação para processos Git no Terminal Integrado. **Nota:** Terminais precisam ser reiniciados após mudança.",
"config.terminalGitEditor": "Controla se o VS Code será o editor Git para processos Git no Terminal Integrado. **Nota:** Terminais precisam ser reiniciados após mudança.",
"config.timeline.showAuthor": "Controla se o autor do commit é mostrado na visualização Timeline.",
"config.timeline.showUncommitted": "Controla se alterações não commitadas são mostradas na Timeline.",
"config.timeline.date": "Controla qual data usar para itens na Timeline.",
"config.timeline.date.committed": "Usar data do commit",
"config.timeline.date.authored": "Usar data de autoria",
"config.useCommitInputAsStashMessage": "Controla se a mensagem da caixa de commit será usada como mensagem padrão de stash.",
"config.showActionButton": "Controla se um botão de ação é mostrado na visualização de Controle de Código Fonte.",
"config.showActionButton.commit": "Mostrar botão de ação para commit quando o branch local tiver arquivos modificados prontos.",
"config.showActionButton.publish": "Mostrar botão de ação para publicar branch local sem branch remoto rastreado.",
"config.showActionButton.sync": "Mostrar botão de ação para sincronizar alterações quando branch local estiver à frente ou atrás do remoto.",
"config.statusLimit": "Controla limite de alterações que podem ser analisadas pelo comando Git status. 0 = sem limite.",
"config.experimental.installGuide": "Melhorias experimentais no fluxo de configuração do Git.",
"config.repositoryScanIgnoredFolders": "Lista de pastas ignoradas ao procurar repositórios Git quando `#git.autoRepositoryDetection#` está `true` ou `subFolders`.",
"config.repositoryScanMaxDepth": "Controla a profundidade usada ao escanear pastas de workspace por repositórios Git quando `#git.autoRepositoryDetection#` está `true` ou `subFolders`. -1 = sem limite.",
"config.useIntegratedAskPass": "Controla se GIT_ASKPASS deve ser sobrescrito para usar versão integrada.",
"config.mergeEditor": "Abrir editor de merge para arquivos atualmente em conflito.",
"config.optimisticUpdate": "Controla se a visualização do Controle de Código Fonte será atualizada de forma otimista após comandos Git.",
"config.openRepositoryInParentFolders": "Controla se um repositório em pastas pai do workspace ou arquivos abertos deve ser aberto.",
"config.openRepositoryInParentFolders.always": "Sempre abrir repositório em pastas pai do workspace ou arquivos abertos.",
"config.openRepositoryInParentFolders.never": "Nunca abrir repositório em pastas pai do workspace ou arquivos abertos.",
"config.openRepositoryInParentFolders.prompt": "Solicitar confirmação antes de abrir repositório em pastas pai do workspace ou arquivos abertos.",
"config.publishBeforeContinueOn": "Controla se estado Git não publicado deve ser publicado ao usar 'Continue Working On' de um repositório Git.",
"config.publishBeforeContinueOn.always": "Sempre publicar estado não publicado ao usar 'Continue Working On'.",
"config.publishBeforeContinueOn.never": "Nunca publicar estado não publicado ao usar 'Continue Working On'.",
"config.publishBeforeContinueOn.prompt": "Solicitar publicação do estado não publicado ao usar 'Continue Working On'.",
"config.similarityThreshold": "Controla limiar do índice de similaridade (quantidade de adições/remoções comparadas ao tamanho do arquivo) para considerar alterações em arquivos adicionados/removidos como renome. **Nota:** Requer Git `2.18.0` ou superior.",
"config.blameEditorDecoration.enabled": "Controla se informações de blame são mostradas no editor usando decorações.",
"config.blameEditorDecoration.template": "Template da decoração de informações de blame. Variáveis suportadas:\n\n* `hash`: Hash do commit\n* `hashShort`: Primeiros N caracteres do hash (definido em `#git.commitShortHashLength#`)\n* `subject`: Primeira linha da mensagem do commit\n* `authorName`: Nome do autor\n* `authorEmail`: Email do autor\n* `authorDate`: Data do commit\n* `authorDateAgo`: Diferença de tempo entre agora e a data do commit",
"config.blameStatusBarItem.enabled": "Controla se informações de blame são mostradas na barra de status.",
"config.blameStatusBarItem.template": "Template para informações de blame na barra de status. Variáveis suportadas:\n\n* `hash`: Hash do commit\n* `hashShort`: Primeiros N caracteres do hash\n* `subject`: Primeira linha da mensagem do commit\n* `authorName`: Nome do autor\n* `authorEmail`: Email do autor\n* `authorDate`: Data do commit\n* `authorDateAgo`: Diferença de tempo entre agora e a data do commit",
"config.commitShortHashLength": "Controla o tamanho do hash curto do commit.",
"config.diagnosticsCommitHook.enabled": "Controla se diagnósticos não resolvidos devem ser verificados antes do commit.",
"config.diagnosticsCommitHook.sources": "Controla lista de fontes (**Item**) e severidade mínima (**Value**) a serem consideradas antes do commit. **Nota:** Para ignorar diagnósticos de uma fonte específica, adicione à lista e defina severidade mínima como `none`.",
"config.discardUntrackedChangesToTrash": "Controla se descartar alterações não rastreadas move arquivos para Lixeira (Windows), Trash (macOS, Linux) ao invés de deletar permanentemente. **Nota:** Sem efeito em repositório remoto ou Linux via Snap.",
"config.showReferenceDetails": "Controla se detalhes do último commit de refs Git são mostrados nos seletores de checkout, branch e tag.",
"submenu.explorer": "Git",
"submenu.commit": "Commit",
"submenu.commit.amend": "Amend",
"submenu.commit.signoff": "Sign Off",
"submenu.changes": "Alterações",
"submenu.pullpush": "Pull, Push",
"submenu.branch": "Branch",
"submenu.remotes": "Remoto",
"submenu.stash": "Stash",
"submenu.tags": "Tags",
"submenu.worktrees": "Worktrees",
"colors.added": "Cor para recursos adicionados.",
"colors.modified": "Cor para recursos modificados.",
"colors.stageModified": "Cor para recursos modificados e staged.",
"colors.stageDeleted": "Cor para recursos deletados e staged.",
"colors.deleted": "Cor para recursos deletados.",
"colors.renamed": "Cor para recursos renomeados ou copiados.",
"colors.untracked": "Cor para recursos não rastreados.",
"colors.ignored": "Cor para recursos ignorados.",
"colors.conflict": "Cor para recursos com conflitos.",
"colors.submodule": "Cor para recursos de submódulos.",
"colors.incomingAdded": "Cor para recurso entrante adicionado.",
"colors.incomingDeleted": "Cor para recurso entrante deletado.",
"colors.incomingRenamed": "Cor para recurso entrante renomeado.",
"colors.incomingModified": "Cor para recurso entrante modificado.",
"colors.blameEditorDecoration": "Cor para decoração de blame no editor.",
"view.workbench.scm.missing.windows": {
    "message": "[Baixar Git para Windows](https://git-scm.com/download/win)\nApós instalar, por favor [recarregar](command:workbench.action.reloadWindow) (ou [solucionar problemas](command:git.showOutput)). Provedores de controle de código adicionais podem ser instalados [no Marketplace](command:workbench.extensions.search?%22%40category%3A%5C%22scm%20providers%5C%22%22).",
    "comment": [
        "{Locked='](command:workbench.action.reloadWindow'}",
        "{Locked='](command:git.showOutput'}",
        "{Locked='](command:workbench.extensions.search?%22%40category%3A%5C%22scm%20providers%5C%22%22'}",
        "Não traduzir a parte 'command:*' dentro de '(..)'. É sintaxe interna do VS Code",
        "Certifique-se de não haver espaço entre colchete direito e parêntese esquerdo:  ]( sintaxe interna de links"
    ]
},
	"view.workbench.scm.missing.mac": {
    "message": "[Baixar Git para macOS](https://git-scm.com/download/mac)\nApós instalar, por favor [recarregar](command:workbench.action.reloadWindow) (ou [solucionar problemas](command:git.showOutput)). Provedores de controle de código adicionais podem ser instalados [no Marketplace](command:workbench.extensions.search?%22%40category%3A%5C%22scm%20providers%5C%22%22).",
    "comment": [
        "{Locked='](command:workbench.action.reloadWindow'}",
        "{Locked='](command:git.showOutput'}",
        "{Locked='](command:workbench.extensions.search?%22%40category%3A%5C%22scm%20providers%5C%22%22'}",
        "Não traduzir a parte 'command:*' dentro de '(..)'. É sintaxe interna do VS Code",
        "Certifique-se de não haver espaço entre colchete direito e parêntese esquerdo:  ]( sintaxe interna de links"
    ]
},
"view.workbench.scm.missing.linux": {
    "message": "O controle de código depende do Git estar instalado.\n[Baixar Git para Linux](https://git-scm.com/download/linux)\nApós instalar, por favor [recarregar](command:workbench.action.reloadWindow) (ou [solucionar problemas](command:git.showOutput)). Provedores de controle de código adicionais podem ser instalados [no Marketplace](command:workbench.extensions.search?%22%40category%3A%5C%22scm%20providers%5C%22%22).",
    "comment": [
        "{Locked='](command:workbench.action.reloadWindow'}",
        "{Locked='](command:git.showOutput'}",
        "{Locked='](command:workbench.extensions.search?%22%40category%3A%5C%22scm%20providers%5C%22%22'}",
        "Não traduzir a parte 'command:*' dentro de '(..)'. É sintaxe interna do VS Code",
        "Certifique-se de não haver espaço entre colchete direito e parêntese esquerdo:  ]( sintaxe interna de links"
    ]
},
"view.workbench.scm.missing": {
    "message": "Instale o Git, um sistema de controle de versão popular, para rastrear alterações no código e colaborar com outros. Saiba mais nos nossos [Guias do Git](https://aka.ms/vscode-scm).",
    "comment": [
        "{Locked='](https://aka.ms/vscode-scm'}",
        "Certifique-se de não haver espaço entre colchete direito e parêntese esquerdo:  ]( sintaxe interna de links"
    ]
},
"view.workbench.scm.disabled": {
    "message": "Se você deseja usar recursos do Git, habilite o Git em suas [configurações](command:workbench.action.openSettings?%5B%22git.enabled%22%5D).\nPara aprender mais sobre como usar Git e controle de código no VS Code [leia nossa documentação](https://aka.ms/vscode-scm).",
    "comment": [
        "{Locked='](command:workbench.action.openSettings?%5B%22git.enabled%22%5D'}",
        "Não traduzir a parte 'command:*' dentro de '(..)'. É sintaxe interna do VS Code",
        "Certifique-se de não haver espaço entre colchete direito e parêntese esquerdo:  ]( sintaxe interna de links"
    ]
},
"view.workbench.scm.empty": {
    "message": "Para usar recursos do Git, você pode abrir uma pasta contendo um repositório Git ou clonar a partir de uma URL.\n[Abrir Pasta](command:vscode.openFolder)\n[Clonar Repositório](command:git.cloneRecursive)\nPara aprender mais sobre como usar Git e controle de código no VS Code [leia nossa documentação](https://aka.ms/vscode-scm).",
    "comment": [
        "{Locked='](command:vscode.openFolder'}",
        "Não traduzir a parte 'command:*' dentro de '(..)'. É sintaxe interna do VS Code",
        "Certifique-se de não haver espaço entre colchete direito e parêntese esquerdo:  ]( sintaxe interna de links"
    ]
},
"view.workbench.scm.folder": {
    "message": "A pasta aberta atualmente não possui um repositório Git. Você pode inicializar um repositório, habilitando recursos de controle de código do Git.\n[Inicializar Repositório](command:git.init?%5Btrue%5D)\nPara aprender mais sobre como usar Git e controle de código no VS Code [leia nossa documentação](https://aka.ms/vscode-scm).",
    "comment": [
        "{Locked='](command:git.init?%5Btrue%5D'}",
        "Não traduzir a parte 'command:*' dentro de '(..)'. É sintaxe interna do VS Code",
        "Certifique-se de não haver espaço entre colchete direito e parêntese esquerdo:  ]( sintaxe interna de links"
    ]
},
"view.workbench.scm.workspace": {
    "message": "O workspace aberto atualmente não possui pastas com repositórios Git. Você pode inicializar um repositório em uma pasta, habilitando recursos de controle de código do Git.\n[Inicializar Repositório](command:git.init)\nPara aprender mais sobre como usar Git e controle de código no VS Code [leia nossa documentação](https://aka.ms/vscode-scm).",
    "comment": [
        "{Locked='](command:git.init'}",
        "Não traduzir a parte 'command:*' dentro de '(..)'. É sintaxe interna do VS Code",
        "Certifique-se de não haver espaço entre colchete direito e parêntese esquerdo:  ]( sintaxe interna de links"
    ]
},
"view.workbench.scm.emptyWorkspace": {
    "message": "O workspace aberto atualmente não possui pastas com repositórios Git.\n[Adicionar Pasta ao Workspace](command:workbench.action.addRootFolder)\nPara aprender mais sobre como usar Git e controle de código no VS Code [leia nossa documentação](https://aka.ms/vscode-scm).",
    "comment": [
        "{Locked='](command:workbench.action.addRootFolder'}",
        "Não traduzir a parte 'command:*' dentro de '(..)'. É sintaxe interna do VS Code",
        "Certifique-se de não haver espaço entre colchete direito e parêntese esquerdo:  ]( sintaxe interna de links"
    ]
},
"view.workbench.scm.scanFolderForRepositories": {
    "message": "Procurando repositórios Git na pasta..."
},
"view.workbench.scm.scanWorkspaceForRepositories": {
    "message": "Procurando repositórios Git no workspace..."
},
"view.workbench.scm.repositoryInParentFolders": {
    "message": "Um repositório Git foi encontrado nas pastas pai do workspace ou dos arquivos abertos.\n[Abrir Repositório](command:git.openRepositoriesInParentFolders)\nUse a configuração [git.openRepositoryInParentFolders](command:workbench.action.openSettings?%5B%22git.openRepositoryInParentFolders%22%5D) para controlar se repositórios Git em pastas pai do workspace ou arquivos abertos devem ser abertos. Para saber mais [leia nossa documentação](https://aka.ms/vscode-git-repository-in-parent-folders).",
    "comment": [
        "{Locked='](command:git.openRepositoriesInParentFolders'}",
        "{Locked='](command:workbench.action.openSettings?%5B%22git.openRepositoryInParentFolders%22%5D'}",
        "Não traduzir a parte 'command:*' dentro de '(..)'. É sintaxe interna do VS Code",
        "Certifique-se de não haver espaço entre colchete direito e parêntese esquerdo:  ]( sintaxe interna de links"
    ]
},
"view.workbench.scm.repositoriesInParentFolders": {
    "message": "Repositórios Git foram encontrados nas pastas pai do workspace ou dos arquivos abertos.\n[Abrir Repositório](command:git.openRepositoriesInParentFolders)\nUse a configuração [git.openRepositoryInParentFolders](command:workbench.action.openSettings?%5B%22git.openRepositoryInParentFolders%22%5D) para controlar se repositórios Git em pastas pai do workspace ou arquivos abertos devem ser abertos. Para saber mais [leia nossa documentação](https://aka.ms/vscode-git-repository-in-parent-folders).",
    "comment": [
        "{Locked='](command:git.openRepositoriesInParentFolders'}",
        "{Locked='](command:workbench.action.openSettings?%5B%22git.openRepositoryInParentFolders%22%5D'}",
        "Não traduzir a parte 'command:*' dentro de '(..)'. É sintaxe interna do VS Code",
        "Certifique-se de não haver espaço entre colchete direito e parêntese esquerdo:  ]( sintaxe interna de links"
    ]
},
"view.workbench.scm.unsafeRepository": {
    "message": "O repositório Git detectado é potencialmente inseguro, pois a pasta é de propriedade de outro usuário.\n[Gerenciar Repositórios Inseguros](command:git.manageUnsafeRepositories)\nPara saber mais sobre repositórios inseguros [leia nossa documentação](https://aka.ms/vscode-git-unsafe-repository).",
    "comment": [
        "{Locked='](command:git.manageUnsafeRepositories'}",
        "Não traduzir a parte 'command:*' dentro de '(..)'. É sintaxe interna do VS Code",
        "Certifique-se de não haver espaço entre colchete direito e parêntese esquerdo:  ]( sintaxe interna de links"
    ]
},
"view.workbench.scm.unsafeRepositories": {
    "message": "Os repositórios Git detectados são potencialmente inseguros, pois as pastas são de propriedade de outro usuário.\n[Gerenciar Repositórios Inseguros](command:git.manageUnsafeRepositories)\nPara saber mais sobre repositórios inseguros [leia nossa documentação](https://aka.ms/vscode-git-unsafe-repository).",
    "comment": [
        "{Locked='](command:git.manageUnsafeRepositories'}",
        "Não traduzir a parte 'command:*' dentro de '(..)'. É sintaxe interna do VS Code",
        "Certifique-se de não haver espaço entre colchete direito e parêntese esquerdo:  ]( sintaxe interna de links"
    ]
},
"view.workbench.scm.closedRepository": {
    "message": "Um repositório Git foi encontrado que estava previamente fechado.\n[Reabrir Repositório Fechado](command:git.reopenClosedRepositories)\nPara aprender mais sobre como usar Git e controle de código no VS Code [leia nossa documentação](https://aka.ms/vscode-scm).",
    "comment": [
        "{Locked='](command:git.reopenClosedRepositories'}",
        "Não traduzir a parte 'command:*' dentro de '(..)'. É sintaxe interna do VS Code",
        "Certifique-se de não haver espaço entre colchete direito e parêntese esquerdo:  ]( sintaxe interna de links"
    ]
},
"view.workbench.scm.closedRepositories": {
    "message": "Repositórios Git foram encontrados que estavam previamente fechados.\n[Reabrir Repositórios Fechados](command:git.reopenClosedRepositories)\nPara aprender mais sobre como usar Git e controle de código no VS Code [leia nossa documentação](https://aka.ms/vscode-scm).",
    "comment": [
        "{Locked='](command:git.reopenClosedRepositories'}",
        "Não traduzir a parte 'command:*' dentro de '(..)'. É sintaxe interna do VS Code",
        "Certifique-se de não haver espaço entre colchete direito e parêntese esquerdo:  ]( sintaxe interna de links"
    ]
},
"view.workbench.cloneRepository": {
    "message": "Você pode clonar um repositório localmente.\n[Clonar Repositório](command:git.clone 'Clone um repositório após a extensão Git ser ativada')",
    "comment": [
        "{Locked='](command:git.clone'}",
        "Não traduzir a parte 'command:*' dentro de '(..)'. É sintaxe interna do VS Code",
        "Certifique-se de não haver espaço entre colchete direito e parêntese esquerdo:  ]( sintaxe interna de links"
    ]
},
"view.workbench.learnMore": "Para saber mais sobre como usar Git e controle de código no VS Code [leia nossa documentação](https://aka.ms/vscode-scm)."
}
